optimalflow/__init__.py
optimalflow/autoCV.py
optimalflow/autoFS.py
optimalflow/autoPP.py
optimalflow/autoPipe.py
optimalflow/autoViz.py
optimalflow/estimatorCV.py
optimalflow/funcPP.py
optimalflow/parameters.json
optimalflow/reset_parameters.json
optimalflow/selectorFS.py
optimalflow/utilis_func.py
optimalflow/webapp/app.py
optimalflow/webapp/reset_settings.json
optimalflow/webapp/settings.json
optimalflow/webapp/settings_script.py
optimalflow/webapp/webapp.json
optimalflow/webapp/webapp_script.py
optimalflow/webapp/input/breast_cancer.csv
optimalflow/webapp/static/css/bootstrap-grid.css
optimalflow/webapp/static/css/bootstrap-grid.css.map
optimalflow/webapp/static/css/bootstrap-grid.min.css
optimalflow/webapp/static/css/bootstrap-grid.min.css.map
optimalflow/webapp/static/css/bootstrap-reboot.css
optimalflow/webapp/static/css/bootstrap-reboot.css.map
optimalflow/webapp/static/css/bootstrap-reboot.min.css
optimalflow/webapp/static/css/bootstrap-reboot.min.css.map
optimalflow/webapp/static/css/bootstrap.css
optimalflow/webapp/static/css/bootstrap.css.map
optimalflow/webapp/static/css/bootstrap.min.css
optimalflow/webapp/static/css/bootstrap.min.css.map
optimalflow/webapp/static/css/heroic-features.css
optimalflow/webapp/static/img/OptimalFlow_Logo.png
optimalflow/webapp/static/img/OptimalFlow_Workflow.PNG
optimalflow/webapp/static/img/Profile.jpg
optimalflow/webapp/static/img/no-cls-output.html
optimalflow/webapp/static/js/bootstrap.bundle.js
optimalflow/webapp/static/js/bootstrap.bundle.js.map
optimalflow/webapp/static/js/bootstrap.bundle.min.js
optimalflow/webapp/static/js/bootstrap.bundle.min.js.map
optimalflow/webapp/static/js/bootstrap.js
optimalflow/webapp/static/js/bootstrap.js.map
optimalflow/webapp/static/js/bootstrap.min.js
optimalflow/webapp/static/js/bootstrap.min.js.map
optimalflow/webapp/static/js/dependent-selects.js
optimalflow/webapp/templates/about.html
optimalflow/webapp/templates/base.html
optimalflow/webapp/templates/diagram.html
optimalflow-0.1.11.dist-info/LICENSE
optimalflow-0.1.11.dist-info/METADATA
optimalflow-0.1.11.dist-info/WHEEL
optimalflow-0.1.11.dist-info/top_level.txt
optimalflow-0.1.11.dist-info/RECORD
