Metadata-Version: 2.1
Name: optimalflow
Version: 0.1.11
Summary: OptimalFlow is an Omni-ensemble Automated Machine Learning toolkit to help data scientists building optimal models in easy way, and automate Machine Learning workflow with simple code.
Home-page: https://github.com/tonyleidong/OptimalFlow
Author: Tony Dong
Author-email: tonyleidong@gmail.com
License: UNKNOWN
Keywords: automated machine learning,features selection,model selection,AutoML,omni-ensemble machine learning,Machine Learning Web App
Platform: UNKNOWN
Classifier: Programming Language :: Python :: 3.8
Classifier: License :: OSI Approved :: MIT License
Classifier: Operating System :: OS Independent
Requires-Python: >=3.7
Requires-Dist: pandas
Requires-Dist: scikit-learn
Requires-Dist: statsmodels
Requires-Dist: scipy
Requires-Dist: joblib
Requires-Dist: category-encoders
Requires-Dist: plotly
Requires-Dist: flask
Requires-Dist: wtforms
Requires-Dist: werkzeug
Requires-Dist: matplotlib
